kuscia/__init__.py
kuscia/datamesh/__init__.py
kuscia/datamesh/api.py
kuscia/datamesh/config.py
kuscia/datamesh/datamanager.py
kuscia/datamesh/dataproxy.py
kuscia/deploy/__init__.py
kuscia/deploy/apihelper.py
kuscia/deploy/app.py
kuscia/deploy/appimage.py
kuscia/deploy/deploy.py
kuscia/deploy/dockerhelper.py
kuscia/deploy/instance.py
kuscia/deploy/k8shelper.py
kuscia/deploy/runtime.py
kuscia/deploy/utils.py
kuscia/deploy/container/__init__.py
kuscia/deploy/container/autonomy.py
kuscia/deploy/container/docker_container.py
kuscia/deploy/container/lite.py
kuscia/deploy/container/master.py
kuscia/job/__init__.py
kuscia/job/api.py
kuscia/job/bulitin.py
kuscia/job/task.py
kuscia/proto/__init__.py
kuscia/proto/api/__init__.py
kuscia/proto/api/v1/__init__.py
kuscia/proto/api/v1/interconn/__init__.py
kuscia/proto/api/v1/interconn/common_pb2.py
kuscia/proto/api/v1/interconn/common_pb2_grpc.py
kuscia/proto/api/v1/interconn/job_pb2.py
kuscia/proto/api/v1/interconn/job_pb2_grpc.py
kuscia/proto/api/v1/interconn/task_pb2.py
kuscia/proto/api/v1/interconn/task_pb2_grpc.py
kuscia/proto/api/v1alpha1/__init__.py
kuscia/proto/api/v1alpha1/common_pb2.py
kuscia/proto/api/v1alpha1/common_pb2_grpc.py
kuscia/proto/api/v1alpha1/apilite/__init__.py
kuscia/proto/api/v1alpha1/apilite/domain_pb2.py
kuscia/proto/api/v1alpha1/apilite/domain_pb2_grpc.py
kuscia/proto/api/v1alpha1/apilite/domain_route_pb2.py
kuscia/proto/api/v1alpha1/apilite/domain_route_pb2_grpc.py
kuscia/proto/api/v1alpha1/apilite/health_pb2.py
kuscia/proto/api/v1alpha1/apilite/health_pb2_grpc.py
kuscia/proto/api/v1alpha1/apilite/job_pb2.py
kuscia/proto/api/v1alpha1/apilite/job_pb2_grpc.py
kuscia/proto/api/v1alpha1/appconfig/__init__.py
kuscia/proto/api/v1alpha1/appconfig/app_config_pb2.py
kuscia/proto/api/v1alpha1/appconfig/app_config_pb2_grpc.py
kuscia/proto/api/v1alpha1/confmanager/__init__.py
kuscia/proto/api/v1alpha1/confmanager/certificate_pb2.py
kuscia/proto/api/v1alpha1/confmanager/certificate_pb2_grpc.py
kuscia-0.0.3b0.dist-info/LICENSE
kuscia-0.0.3b0.dist-info/METADATA
kuscia-0.0.3b0.dist-info/WHEEL
kuscia-0.0.3b0.dist-info/top_level.txt
kuscia-0.0.3b0.dist-info/RECORD
