Metadata-Version: 2.1
Name: kuscia
Version: 0.0.3b0
Summary: Protocols for kuscia
Author: secretflow authors
Author-email: secretflow-contact@service.alipay.com
License: Apache 2.0
License-File: LICENSE
